[
  {
    "id": "0080",
    "name": "恒中國",
    "freq": "",
    "price": null,
    "ytd": null,
    "cagr_1y": null,
    "sharpe": null,
    "mdd": null,
    "vol_20d": null,
    "yield_ttm": null,
    "dividend_rate": null
  },
  {
    "id": "0081",
    "name": "恒香港",
    "freq": "",
    "price": null,
    "ytd": null,
    "cagr_1y": null,
    "sharpe": null,
    "mdd": null,
    "vol_20d": null,
    "yield_ttm": null,
    "dividend_rate": null
  },
  {
    "id": "00866",
    "name": "新光Shiller CAPE",
    "freq": "",
    "price": null,
    "ytd": null,
    "cagr_1y": null,
    "sharpe": null,
    "mdd": null,
    "vol_20d": null,
    "yield_ttm": null,
    "dividend_rate": null
  },
  {
    "id": "0060",
    "name": "新台灣",
    "freq": "",
    "price": null,
    "ytd": null,
    "cagr_1y": null,
    "sharpe": null,
    "mdd": null,
    "vol_20d": null,
    "yield_ttm": null,
    "dividend_rate": null
  },
  {
    "id": "00776",
    "name": "新光ICE美國權值",
    "freq": "",
    "price": null,
    "ytd": null,
    "cagr_1y": null,
    "sharpe": null,
    "mdd": null,
    "vol_20d": null,
    "yield_ttm": null,
    "dividend_rate": null
  },
  {
    "id": "00742",
    "name": "新光內需收益",
    "freq": "",
    "price": null,
    "ytd": null,
    "cagr_1y": null,
    "sharpe": null,
    "mdd": null,
    "vol_20d": null,
    "yield_ttm": null,
    "dividend_rate": null
  },
  {
    "id": "00732",
    "name": "國泰RMB短期報酬",
    "freq": "",
    "price": 40.03,
    "ytd": 0.0,
    "cagr_1y": null,
    "sharpe": null,
    "mdd": null,
    "vol_20d": null,
    "yield_ttm": null,
    "dividend_rate": null
  },
  {
    "id": "00767",
    "name": "FH美國金融股",
    "freq": "",
    "price": null,
    "ytd": null,
    "cagr_1y": null,
    "sharpe": null,
    "mdd": null,
    "vol_20d": null,
    "yield_ttm": null,
    "dividend_rate": null
  },
  {
    "id": "00667",
    "name": "元大韓國",
    "freq": "",
    "price": 24.0,
    "ytd": 0.059602649006622585,
    "cagr_1y": null,
    "sharpe": null,
    "mdd": null,
    "vol_20d": null,
    "yield_ttm": null,
    "dividend_rate": null
  },
  {
    "id": "00677U",
    "name": "期富邦VIX",
    "freq": "",
    "price": 5.34,
    "ytd": -0.3650416171224733,
    "cagr_1y": null,
    "sharpe": null,
    "mdd": null,
    "vol_20d": null,
    "yield_ttm": null,
    "dividend_rate": null
  },
  {
    "id": "00649",
    "name": "FH香港",
    "freq": "",
    "price": 20.83,
    "ytd": 0.0296589223924863,
    "cagr_1y": null,
    "sharpe": null,
    "mdd": null,
    "vol_20d": null,
    "yield_ttm": null,
    "dividend_rate": null
  },
  {
    "id": "0059",
    "name": "富邦金融",
    "freq": "",
    "price": 40.47,
    "ytd": 0.05693392530686863,
    "cagr_1y": null,
    "sharpe": null,
    "mdd": null,
    "vol_20d": null,
    "yield_ttm": null,
    "dividend_rate": null
  },
  {
    "id": "0058",
    "name": "富邦發達",
    "freq": "",
    "price": 0.0,
    "ytd": null,
    "cagr_1y": null,
    "sharpe": null,
    "mdd": null,
    "vol_20d": null,
    "yield_ttm": null,
    "dividend_rate": null
  },
  {
    "id": "00738U",
    "name": "期元大道瓊白銀",
    "freq": "",
    "price": 46.82,
    "ytd": -0.21112047177759058,
    "cagr_1y": 0.5401315789473685,
    "sharpe": 1.0579221445549896,
    "mdd": -0.5295090439276485,
    "vol_20d": 6403,
    "yield_ttm": null,
    "dividend_rate": null
  },
  {
    "id": "00757",
    "name": "統一FANG+",
    "freq": "",
    "price": 125.3,
    "ytd": 0.06051629284807441,
    "cagr_1y": 0.2071290944123314,
    "sharpe": 0.9864339224200366,
    "mdd": -0.19305943358595923,
    "vol_20d": 2258,
    "yield_ttm": null,
    "dividend_rate": null
  },
  {
    "id": "00763U",
    "name": "期街口道瓊銅",
    "freq": "",
    "price": 32.94,
    "ytd": 0.05543095161807103,
    "cagr_1y": 0.15215110178384042,
    "sharpe": 0.5961407064120807,
    "mdd": -0.24862553451435554,
    "vol_20d": 876,
    "yield_ttm": null,
    "dividend_rate": null
  },
  {
    "id": "00736",
    "name": "國泰新興市場",
    "freq": "",
    "price": 30.95,
    "ytd": 0.10654272434751522,
    "cagr_1y": 0.31758194976585785,
    "sharpe": 2.0000442716010225,
    "mdd": -0.09525389976767333,
    "vol_20d": 129,
    "yield_ttm": null,
    "dividend_rate": null
  },
  {
    "id": "00850",
    "name": "元大臺灣ESG永續",
    "freq": "",
    "price": 89.25,
    "ytd": 0.6124661246612466,
    "cagr_1y": 1.0460797799174693,
    "sharpe": 3.237606689047507,
    "mdd": -0.10565476190476192,
    "vol_20d": 963,
    "yield_ttm": null,
    "dividend_rate": null
  },
  {
    "id": "00894",
    "name": "中信小資高價30",
    "freq": "",
    "price": 47.06,
    "ytd": 0.7013738250180768,
    "cagr_1y": 1.3839918946301928,
    "sharpe": 3.10137511102984,
    "mdd": -0.10444704505558808,
    "vol_20d": 2092,
    "yield_ttm": null,
    "dividend_rate": null
  },
  {
    "id": "00895",
    "name": "富邦未來車",
    "freq": "",
    "price": 50.6,
    "ytd": 0.2937867553055485,
    "cagr_1y": 0.6771627444481272,
    "sharpe": 2.4631583878702443,
    "mdd": -0.10954726718273519,
    "vol_20d": 744,
    "yield_ttm": null,
    "dividend_rate": null
  },
  {
    "id": "00898",
    "name": "國泰基因免疫革命",
    "freq": "",
    "price": 9.3,
    "ytd": 0.1862244897959185,
    "cagr_1y": 0.5604026845637585,
    "sharpe": 2.132774006392045,
    "mdd": -0.1019698725376594,
    "vol_20d": 982,
    "yield_ttm": null,
    "dividend_rate": null
  },
  {
    "id": "00899",
    "name": "FT潔淨能源",
    "freq": "",
    "price": 25.6,
    "ytd": 0.27680798004987534,
    "cagr_1y": 0.8156028368794328,
    "sharpe": 2.721816251709884,
    "mdd": -0.14921900963775336,
    "vol_20d": 144,
    "yield_ttm": null,
    "dividend_rate": null
  },
  {
    "id": "00901",
    "name": "永豐智能車供應鏈",
    "freq": "",
    "price": 45.85,
    "ytd": 0.8281499202551836,
    "cagr_1y": 1.2925,
    "sharpe": 2.8529379117969644,
    "mdd": -0.16940671908506083,
    "vol_20d": 512,
    "yield_ttm": null,
    "dividend_rate": null
  },
  {
    "id": "00902",
    "name": "中信電池及儲能",
    "freq": "",
    "price": 14.79,
    "ytd": 0.13246554364471658,
    "cagr_1y": 0.8985879332477534,
    "sharpe": 2.4322228309663103,
    "mdd": -0.16647662485746864,
    "vol_20d": 2018,
    "yield_ttm": null,
    "dividend_rate": null
  },
  {
    "id": "00903",
    "name": "富邦元宇宙",
    "freq": "",
    "price": 20.43,
    "ytd": 0.1707736389684814,
    "cagr_1y": 0.412863070539419,
    "sharpe": 1.5344786882935488,
    "mdd": -0.2017259978425026,
    "vol_20d": 404,
    "yield_ttm": null,
    "dividend_rate": null
  },
  {
    "id": "00905",
    "name": "FT臺灣Smart",
    "freq": "",
    "price": 27.4,
    "ytd": 0.574712643678161,
    "cagr_1y": 1.025129342202513,
    "sharpe": 3.1458654040971634,
    "mdd": -0.09749034749034748,
    "vol_20d": 1977,
    "yield_ttm": null,
    "dividend_rate": null
  },
  {
    "id": "00908",
    "name": "富邦入息REITs+",
    "freq": "",
    "price": 15.2,
    "ytd": 0.09589041095890412,
    "cagr_1y": 0.1856474258970358,
    "sharpe": 1.698627397108009,
    "mdd": -0.0875862068965517,
    "vol_20d": 157,
    "yield_ttm": null,
    "dividend_rate": null
  },
  {
    "id": "00909",
    "name": "國泰數位支付服務",
    "freq": "",
    "price": 49.11,
    "ytd": 0.2637673700463201,
    "cagr_1y": 0.5419152276295133,
    "sharpe": 1.2524307405332185,
    "mdd": -0.3169260700389105,
    "vol_20d": 1989,
    "yield_ttm": null,
    "dividend_rate": null
  },
  {
    "id": "00910",
    "name": "第一金太空衛星",
    "freq": "",
    "price": 59.25,
    "ytd": 0.3487366264511723,
    "cagr_1y": 0.8749999999999999,
    "sharpe": 1.7396531832328719,
    "mdd": -0.3479249573621376,
    "vol_20d": 6301,
    "yield_ttm": null,
    "dividend_rate": null
  },
  {
    "id": "00913",
    "name": "兆豐台灣晶圓製造",
    "freq": "",
    "price": 52.3,
    "ytd": 1.097874047332531,
    "cagr_1y": 1.6494427558257347,
    "sharpe": 3.205222939365293,
    "mdd": -0.16363636363636358,
    "vol_20d": 2996,
    "yield_ttm": null,
    "dividend_rate": null
  },
  {
    "id": "00917",
    "name": "中信特選金融",
    "freq": "",
    "price": 22.15,
    "ytd": -0.13510347520499807,
    "cagr_1y": 0.028319405756731638,
    "sharpe": 0.2531109322672928,
    "mdd": -0.37327044025157236,
    "vol_20d": 928,
    "yield_ttm": null,
    "dividend_rate": null
  },
  {
    "id": "00918",
    "name": "大華優利高填息30",
    "freq": "季配",
    "price": 31.43,
    "ytd": 0.39009287925696595,
    "cagr_1y": 0.45240295748613674,
    "sharpe": 2.167967675777506,
    "mdd": -0.09736732135394895,
    "vol_20d": 90944,
    "yield_ttm": null,
    "dividend_rate": null
  },
  {
    "id": "00861",
    "name": "元大全球未來通訊",
    "freq": "",
    "price": 93.2,
    "ytd": 0.6687555953446732,
    "cagr_1y": 1.2059171597633136,
    "sharpe": 3.51475995171859,
    "mdd": -0.09590043923865296,
    "vol_20d": 262,
    "yield_ttm": null,
    "dividend_rate": null
  },
  {
    "id": "00875",
    "name": "國泰網路資安",
    "freq": "",
    "price": 48.72,
    "ytd": 0.2615225271879856,
    "cagr_1y": 0.3012820512820513,
    "sharpe": 1.2564891465640275,
    "mdd": -0.14103194103194108,
    "vol_20d": 277,
    "yield_ttm": null,
    "dividend_rate": null
  },
  {
    "id": "00885",
    "name": "富邦越南",
    "freq": "",
    "price": 18.98,
    "ytd": 0.05268996117581804,
    "cagr_1y": 0.5506535947712419,
    "sharpe": 1.8638309200951104,
    "mdd": -0.136008337675873,
    "vol_20d": 3810,
    "yield_ttm": null,
    "dividend_rate": null
  },
  {
    "id": "00733",
    "name": "富邦臺灣中小",
    "freq": "",
    "price": 74.0,
    "ytd": 0.613958560523446,
    "cagr_1y": 0.9180922757905652,
    "sharpe": 2.295074271845686,
    "mdd": -0.11597938144329896,
    "vol_20d": 1067,
    "yield_ttm": null,
    "dividend_rate": null
  },
  {
    "id": "00642U",
    "name": "期元大S&P石油",
    "freq": "",
    "price": 22.84,
    "ytd": 0.5026315789473684,
    "cagr_1y": 0.42660836976889427,
    "sharpe": 0.8995456986227395,
    "mdd": -0.3155354449472096,
    "vol_20d": 6172,
    "yield_ttm": null,
    "dividend_rate": null
  },
  {
    "id": "00643",
    "name": "群益深証中小",
    "freq": "",
    "price": 19.95,
    "ytd": 0.16666666666666652,
    "cagr_1y": 0.6487603305785123,
    "sharpe": 2.591261245878244,
    "mdd": -0.09060402684563762,
    "vol_20d": 3139,
    "yield_ttm": null,
    "dividend_rate": null
  },
  {
    "id": "00643K",
    "name": "群益深証中小+R",
    "freq": "",
    "price": 4.25,
    "ytd": 0.10677083333333337,
    "cagr_1y": null,
    "sharpe": null,
    "mdd": null,
    "vol_20d": 2,
    "yield_ttm": null,
    "dividend_rate": null
  },
  {
    "id": "00645",
    "name": "富邦日本",
    "freq": "",
    "price": 55.9,
    "ytd": 0.16970077422054822,
    "cagr_1y": 0.4166244298023314,
    "sharpe": 1.9017485925240798,
    "mdd": -0.10485792850595782,
    "vol_20d": 285,
    "yield_ttm": null,
    "dividend_rate": null
  },
  {
    "id": "00652",
    "name": "富邦印度",
    "freq": "",
    "price": 33.3,
    "ytd": -0.10651998926750753,
    "cagr_1y": -0.08188585607940463,
    "sharpe": -0.5008885801983007,
    "mdd": -0.16821438047227372,
    "vol_20d": 467,
    "yield_ttm": null,
    "dividend_rate": null
  },
  {
    "id": "00657",
    "name": "國泰日經225",
    "freq": "",
    "price": 80.4,
    "ytd": 0.3581081081081081,
    "cagr_1y": 0.6944151738672287,
    "sharpe": 2.154770384619583,
    "mdd": -0.12536023054755047,
    "vol_20d": 79,
    "yield_ttm": null,
    "dividend_rate": null
  },
  {
    "id": "00657K",
    "name": "國泰日經225+U",
    "freq": "",
    "price": 25.22,
    "ytd": 0.336512983571807,
    "cagr_1y": 0.5284848484848484,
    "sharpe": null,
    "mdd": -1.0,
    "vol_20d": 0,
    "yield_ttm": null,
    "dividend_rate": null
  },
  {
    "id": "00661",
    "name": "元大日經225",
    "freq": "",
    "price": 88.85,
    "ytd": 0.37114197530864196,
    "cagr_1y": 0.7152509652509652,
    "sharpe": 2.196651683834202,
    "mdd": -0.12738017071569274,
    "vol_20d": 161,
    "yield_ttm": null,
    "dividend_rate": null
  },
  {
    "id": "00662",
    "name": "富邦NASDAQ",
    "freq": "",
    "price": 120.4,
    "ytd": 0.17291768144179248,
    "cagr_1y": 0.4198113207547171,
    "sharpe": 2.1942712598001077,
    "mdd": -0.09116945107398565,
    "vol_20d": 6716,
    "yield_ttm": null,
    "dividend_rate": null
  },
  {
    "id": "00635U",
    "name": "期元大S&P黃金",
    "freq": "",
    "price": 42.29,
    "ytd": -0.08936261843238585,
    "cagr_1y": 0.17733853006681508,
    "sharpe": 0.7209174553709187,
    "mdd": -0.31197357555739064,
    "vol_20d": 4472,
    "yield_ttm": null,
    "dividend_rate": null
  },
  {
    "id": "00401A",
    "name": "主動摩根台灣鑫收",
    "freq": "",
    "price": 13.23,
    "ytd": 0.2469368520263903,
    "cagr_1y": null,
    "sharpe": null,
    "mdd": null,
    "vol_20d": 7695,
    "yield_ttm": null,
    "dividend_rate": null
  },
  {
    "id": "00405A",
    "name": "主動富邦台灣龍耀",
    "freq": "",
    "price": 8.9,
    "ytd": -0.06118143459915612,
    "cagr_1y": null,
    "sharpe": null,
    "mdd": null,
    "vol_20d": null,
    "yield_ttm": null,
    "dividend_rate": null
  },
  {
    "id": "00406A",
    "name": "主動中信台灣收益",
    "freq": "",
    "price": 9.85,
    "ytd": 0.02178423236514513,
    "cagr_1y": null,
    "sharpe": null,
    "mdd": null,
    "vol_20d": null,
    "yield_ttm": null,
    "dividend_rate": null
  },
  {
    "id": "00407A",
    "name": "主動凱基台灣",
    "freq": "",
    "price": 9.46,
    "ytd": -0.04251012145748987,
    "cagr_1y": null,
    "sharpe": null,
    "mdd": null,
    "vol_20d": null,
    "yield_ttm": null,
    "dividend_rate": null
  },
  {
    "id": "0053",
    "name": "元大電子",
    "freq": "",
    "price": 236.85,
    "ytd": 0.6809794180269694,
    "cagr_1y": 1.301749271137026,
    "sharpe": 3.1364344640201653,
    "mdd": -0.10758082497212938,
    "vol_20d": 51,
    "yield_ttm": null,
    "dividend_rate": null
  },
  {
    "id": "0061",
    "name": "元大寶滬深",
    "freq": "",
    "price": 25.25,
    "ytd": 0.09544468546637741,
    "cagr_1y": 0.4289756649688737,
    "sharpe": 2.477349384390019,
    "mdd": -0.06340654786572722,
    "vol_20d": 326,
    "yield_ttm": null,
    "dividend_rate": null
  },
  {
    "id": "006205",
    "name": "富邦上証",
    "freq": "",
    "price": 41.52,
    "ytd": 0.05300532589398944,
    "cagr_1y": 0.3617579534273534,
    "sharpe": 2.138644555987107,
    "mdd": -0.07710727969348656,
    "vol_20d": 689,
    "yield_ttm": null,
    "dividend_rate": null
  },
  {
    "id": "006207",
    "name": "復華滬深",
    "freq": "",
    "price": 33.64,
    "ytd": 0.0950520833333334,
    "cagr_1y": 0.4531317494600433,
    "sharpe": 2.4908142647559925,
    "mdd": -0.05904288377874452,
    "vol_20d": 347,
    "yield_ttm": null,
    "dividend_rate": null
  },
  {
    "id": "00625K",
    "name": "富邦上証+R",
    "freq": "",
    "price": 0.0,
    "ytd": null,
    "cagr_1y": null,
    "sharpe": null,
    "mdd": null,
    "vol_20d": null,
    "yield_ttm": null,
    "dividend_rate": null
  },
  {
    "id": "00701",
    "name": "國泰股利精選30",
    "freq": "",
    "price": 39.14,
    "ytd": 0.33949349760438063,
    "cagr_1y": 0.3894213702520411,
    "sharpe": 2.287871848062109,
    "mdd": -0.09090909090909083,
    "vol_20d": 1381,
    "yield_ttm": null,
    "dividend_rate": null
  },
  {
    "id": "00709",
    "name": "富邦歐洲",
    "freq": "",
    "price": 39.3,
    "ytd": 0.06216216216216208,
    "cagr_1y": 0.25438876476220873,
    "sharpe": 1.6086421972950444,
    "mdd": -0.10955126598144892,
    "vol_20d": 81,
    "yield_ttm": null,
    "dividend_rate": null
  },
  {
    "id": "00714",
    "name": "群益道瓊美國地產",
    "freq": "",
    "price": 22.3,
    "ytd": 0.10890104425658882,
    "cagr_1y": 0.19060331019754406,
    "sharpe": 1.4257500963874974,
    "mdd": -0.06688493919550981,
    "vol_20d": 226,
    "yield_ttm": null,
    "dividend_rate": null
  },
  {
    "id": "00717",
    "name": "富邦美國特別股",
    "freq": "",
    "price": 14.77,
    "ytd": -0.0172987358616101,
    "cagr_1y": 0.07028985507246369,
    "sharpe": 1.0896599023788867,
    "mdd": -0.05025773195876285,
    "vol_20d": 178,
    "yield_ttm": null,
    "dividend_rate": null
  },
  {
    "id": "00728",
    "name": "第一金工業30",
    "freq": "",
    "price": 63.15,
    "ytd": 0.6984938138784292,
    "cagr_1y": 1.0766195330483392,
    "sharpe": 3.1083556522954994,
    "mdd": -0.08610438229464869,
    "vol_20d": 145,
    "yield_ttm": null,
    "dividend_rate": null
  },
  {
    "id": "00700",
    "name": "富邦恒生國企",
    "freq": "",
    "price": 15.49,
    "ytd": -0.14655647382920103,
    "cagr_1y": -0.06178073894609335,
    "sharpe": -0.25884497723320776,
    "mdd": -0.21703011422637597,
    "vol_20d": 402,
    "yield_ttm": null,
    "dividend_rate": null
  },
  {
    "id": "00668",
    "name": "國泰美國道瓊",
    "freq": "",
    "price": 60.6,
    "ytd": 0.09386281588447659,
    "cagr_1y": 0.2923864363403711,
    "sharpe": 2.148114810991054,
    "mdd": -0.08973252804141506,
    "vol_20d": 96,
    "yield_ttm": null,
    "dividend_rate": null
  },
  {
    "id": "00668K",
    "name": "國泰美國道瓊+U",
    "freq": "",
    "price": 18.94,
    "ytd": 0.07248018120045306,
    "cagr_1y": 0.18375000000000008,
    "sharpe": null,
    "mdd": -1.0,
    "vol_20d": 0,
    "yield_ttm": null,
    "dividend_rate": null
  },
  {
    "id": "00920",
    "name": "富邦ESG綠色電力",
    "freq": "",
    "price": 25.49,
    "ytd": 0.40363436123348007,
    "cagr_1y": 1.0573042776432604,
    "sharpe": 3.1681146245935325,
    "mdd": -0.0975609756097561,
    "vol_20d": 429,
    "yield_ttm": null,
    "dividend_rate": null
  },
  {
    "id": "00690",
    "name": "兆豐藍籌30",
    "freq": "",
    "price": 78.6,
    "ytd": 0.7572099262240107,
    "cagr_1y": 1.2922134733158355,
    "sharpe": 3.248182391918829,
    "mdd": -0.11333930170098475,
    "vol_20d": 630,
    "yield_ttm": null,
    "dividend_rate": null
  },
  {
    "id": "00692",
    "name": "富邦公司治理",
    "freq": "",
    "price": 90.4,
    "ytd": 0.5708079930495223,
    "cagr_1y": 1.0287253141831239,
    "sharpe": 3.1966814309953544,
    "mdd": -0.10260014054813779,
    "vol_20d": 1902,
    "yield_ttm": null,
    "dividend_rate": null
  },
  {
    "id": "00693U",
    "name": "期街口S&P黃豆",
    "freq": "",
    "price": 20.95,
    "ytd": 0.03661553686293906,
    "cagr_1y": 0.05382293762575455,
    "sharpe": 0.40848595468831345,
    "mdd": -0.11355785837651118,
    "vol_20d": 829,
    "yield_ttm": null,
    "dividend_rate": null
  },
  {
    "id": "00682U",
    "name": "期元大美元指數",
    "freq": "",
    "price": 20.87,
    "ytd": 0.03521825396825401,
    "cagr_1y": 0.05617408906882588,
    "sharpe": null,
    "mdd": -1.0,
    "vol_20d": 11,
    "yield_ttm": null,
    "dividend_rate": null
  },
  {
    "id": "00921",
    "name": "兆豐龍頭等權重",
    "freq": "",
    "price": 22.61,
    "ytd": 0.2897889332572731,
    "cagr_1y": 0.36286919831223624,
    "sharpe": 1.8948895177397809,
    "mdd": -0.07442116868798243,
    "vol_20d": 527,
    "yield_ttm": null,
    "dividend_rate": null
  },
  {
    "id": "00960",
    "name": "野村全球航運龍頭",
    "freq": "",
    "price": 16.94,
    "ytd": 0.17557251908396954,
    "cagr_1y": 0.26796407185628757,
    "sharpe": 1.455870042526819,
    "mdd": -0.08938244853737823,
    "vol_20d": 751,
    "yield_ttm": null,
    "dividend_rate": null
  },
  {
    "id": "00971",
    "name": "野村美國研發龍頭",
    "freq": "",
    "price": 16.52,
    "ytd": 0.0267246737103791,
    "cagr_1y": 0.18084345961400997,
    "sharpe": 1.0801312008396173,
    "mdd": -0.17476851851851857,
    "vol_20d": 452,
    "yield_ttm": null,
    "dividend_rate": null
  },
  {
    "id": "009800",
    "name": "中信NASDAQ",
    "freq": "",
    "price": 13.0,
    "ytd": 0.1701170117011702,
    "cagr_1y": 0.4115092290988055,
    "sharpe": 2.2180545334149695,
    "mdd": -0.09074889867841404,
    "vol_20d": 2134,
    "yield_ttm": null,
    "dividend_rate": null
  },
  {
    "id": "009805",
    "name": "新光美國電力基建",
    "freq": "",
    "price": 16.89,
    "ytd": 0.3609991941982273,
    "cagr_1y": 0.6334622823984527,
    "sharpe": 2.255035749956375,
    "mdd": -0.09545715928694652,
    "vol_20d": 11543,
    "yield_ttm": null,
    "dividend_rate": null
  },
  {
    "id": "00926",
    "name": "凱基全球菁英55",
    "freq": "",
    "price": 24.35,
    "ytd": 0.04461604461604474,
    "cagr_1y": 0.20484908461157844,
    "sharpe": 1.3474111107549154,
    "mdd": -0.11383748994368456,
    "vol_20d": 857,
    "yield_ttm": null,
    "dividend_rate": null
  },
  {
    "id": "00938",
    "name": "凱基優選30",
    "freq": "",
    "price": 24.18,
    "ytd": 0.38646788990825676,
    "cagr_1y": 0.678001387925052,
    "sharpe": 3.293916190636989,
    "mdd": -0.08422120750887875,
    "vol_20d": 2196,
    "yield_ttm": null,
    "dividend_rate": null
  },
  {
    "id": "00947",
    "name": "台新臺灣IC設計",
    "freq": "",
    "price": 38.34,
    "ytd": 1.0221518987341773,
    "cagr_1y": 1.859060402684564,
    "sharpe": 2.912509278474897,
    "mdd": -0.15369799691833597,
    "vol_20d": 10964,
    "yield_ttm": null,
    "dividend_rate": null
  },
  {
    "id": "00949",
    "name": "復華日本龍頭",
    "freq": "",
    "price": 20.29,
    "ytd": 0.10934937124111536,
    "cagr_1y": 0.2956577266922094,
    "sharpe": 1.4727942930447802,
    "mdd": -0.10105363984674327,
    "vol_20d": 985,
    "yield_ttm": null,
    "dividend_rate": null
  },
  {
    "id": "00984D",
    "name": "主動聯博全球非投",
    "freq": "",
    "price": 10.17,
    "ytd": 0.015984015984015998,
    "cagr_1y": null,
    "sharpe": null,
    "mdd": null,
    "vol_20d": 12724,
    "yield_ttm": null,
    "dividend_rate": null
  },
  {
    "id": "00986A",
    "name": "主動台新龍頭成長",
    "freq": "",
    "price": 15.14,
    "ytd": 0.313096270598439,
    "cagr_1y": 0.5079681274900401,
    "sharpe": 2.2267586514953885,
    "mdd": -0.09473684210526316,
    "vol_20d": 695,
    "yield_ttm": null,
    "dividend_rate": null
  },
  {
    "id": "00987A",
    "name": "主動台新優勢成長",
    "freq": "",
    "price": 16.4,
    "ytd": 0.6221562809099901,
    "cagr_1y": null,
    "sharpe": null,
    "mdd": null,
    "vol_20d": 5433,
    "yield_ttm": null,
    "dividend_rate": null
  },
  {
    "id": "00988A",
    "name": "主動統一全球創新",
    "freq": "",
    "price": 21.45,
    "ytd": 1.1279761904761905,
    "cagr_1y": null,
    "sharpe": null,
    "mdd": null,
    "vol_20d": 111380,
    "yield_ttm": null,
    "dividend_rate": null
  },
  {
    "id": "00993A",
    "name": "主動安聯台灣",
    "freq": "",
    "price": 13.51,
    "ytd": 0.3660262891809908,
    "cagr_1y": null,
    "sharpe": null,
    "mdd": null,
    "vol_20d": 10840,
    "yield_ttm": null,
    "dividend_rate": null
  },
  {
    "id": "00994A",
    "name": "主動第一金台股優",
    "freq": "",
    "price": 17.17,
    "ytd": 0.7067594433399603,
    "cagr_1y": null,
    "sharpe": null,
    "mdd": null,
    "vol_20d": 10882,
    "yield_ttm": null,
    "dividend_rate": null
  },
  {
    "id": "00995A",
    "name": "主動中信台灣卓越",
    "freq": "",
    "price": 17.32,
    "ytd": 0.7030481809242871,
    "cagr_1y": null,
    "sharpe": null,
    "mdd": null,
    "vol_20d": 7226,
    "yield_ttm": null,
    "dividend_rate": null
  },
  {
    "id": "00996A",
    "name": "主動兆豐台灣豐收",
    "freq": "",
    "price": 15.33,
    "ytd": 0.47120921305182345,
    "cagr_1y": null,
    "sharpe": null,
    "mdd": null,
    "vol_20d": 11156,
    "yield_ttm": null,
    "dividend_rate": null
  },
  {
    "id": "00997A",
    "name": "主動群益美國增長",
    "freq": "",
    "price": 13.8,
    "ytd": 0.295774647887324,
    "cagr_1y": null,
    "sharpe": null,
    "mdd": null,
    "vol_20d": 26810,
    "yield_ttm": null,
    "dividend_rate": null
  },
  {
    "id": "00983D",
    "name": "主動富邦複合收益",
    "freq": "",
    "price": 10.2,
    "ytd": -0.005847953216374317,
    "cagr_1y": null,
    "sharpe": null,
    "mdd": null,
    "vol_20d": 1141,
    "yield_ttm": null,
    "dividend_rate": null
  },
  {
    "id": "00983A",
    "name": "主動中信ARK創新",
    "freq": "",
    "price": 12.04,
    "ytd": 0.01346801346801333,
    "cagr_1y": 0.15880654475457157,
    "sharpe": 0.6575087959120895,
    "mdd": -0.25970149253731345,
    "vol_20d": 4805,
    "yield_ttm": null,
    "dividend_rate": null
  },
  {
    "id": "00982T",
    "name": "平衡兆豐台美動能",
    "freq": "",
    "price": 15.61,
    "ytd": 0.5229268292682926,
    "cagr_1y": null,
    "sharpe": null,
    "mdd": null,
    "vol_20d": 107,
    "yield_ttm": null,
    "dividend_rate": null
  },
  {
    "id": "00980A",
    "name": "主動野村臺灣優選",
    "freq": "",
    "price": 23.65,
    "ytd": 0.5467625899280576,
    "cagr_1y": 1.09849157054126,
    "sharpe": 2.936247046152268,
    "mdd": -0.11313717364276836,
    "vol_20d": 12157,
    "yield_ttm": null,
    "dividend_rate": null
  },
  {
    "id": "009812",
    "name": "野村日本東證",
    "freq": "",
    "price": 12.25,
    "ytd": 0.14593077642656693,
    "cagr_1y": null,
    "sharpe": null,
    "mdd": null,
    "vol_20d": 810,
    "yield_ttm": null,
    "dividend_rate": null
  },
  {
    "id": "009818",
    "name": "華南永昌NASDAQxT",
    "freq": "",
    "price": 19.45,
    "ytd": 0.3088829071332436,
    "cagr_1y": null,
    "sharpe": null,
    "mdd": null,
    "vol_20d": 443,
    "yield_ttm": null,
    "dividend_rate": null
  },
  {
    "id": "00981A",
    "name": "主動統一台股增長",
    "freq": "",
    "price": 29.94,
    "ytd": 0.7705499704316973,
    "cagr_1y": 1.734246575342466,
    "sharpe": 3.3110458192008947,
    "mdd": -0.09142475809142471,
    "vol_20d": 269833,
    "yield_ttm": null,
    "dividend_rate": null
  },
  {
    "id": "00981T",
    "name": "平衡凱基雙核收息",
    "freq": "",
    "price": 12.23,
    "ytd": 0.1483568075117371,
    "cagr_1y": null,
    "sharpe": null,
    "mdd": null,
    "vol_20d": 4194,
    "yield_ttm": null,
    "dividend_rate": null
  },
  {
    "id": "009820",
    "name": "元大納斯達克精選",
    "freq": "",
    "price": 9.79,
    "ytd": -0.020020020020020127,
    "cagr_1y": null,
    "sharpe": null,
    "mdd": null,
    "vol_20d": 21953,
    "yield_ttm": null,
    "dividend_rate": null
  },
  {
    "id": "009821",
    "name": "野村稀土關鍵資源",
    "freq": "",
    "price": 14.24,
    "ytd": -0.06806282722513084,
    "cagr_1y": null,
    "sharpe": null,
    "mdd": null,
    "vol_20d": null,
    "yield_ttm": null,
    "dividend_rate": null
  },
  {
    "id": "00982A",
    "name": "主動群益台灣強棒",
    "freq": "",
    "price": 23.65,
    "ytd": 0.6187542778918549,
    "cagr_1y": 1.1757129714811407,
    "sharpe": 2.7021080909158135,
    "mdd": -0.13409703504043127,
    "vol_20d": 39864,
    "yield_ttm": null,
    "dividend_rate": null
  },
  {
    "id": "00982D",
    "name": "主動富邦動態入息",
    "freq": "",
    "price": 10.05,
    "ytd": -0.011799410029498449,
    "cagr_1y": null,
    "sharpe": null,
    "mdd": null,
    "vol_20d": 946,
    "yield_ttm": null,
    "dividend_rate": null
  },
  {
    "id": "009819",
    "name": "中信數據及電力",
    "freq": "",
    "price": 10.15,
    "ytd": -0.19059011164274314,
    "cagr_1y": null,
    "sharpe": null,
    "mdd": null,
    "vol_20d": 20793,
    "yield_ttm": null,
    "dividend_rate": null
  }
]